Topsis_Shaurya_101903125/101903125.py
Topsis_Shaurya_101903125/__init__.py
Topsis_Shaurya_101903125-0.0.1.dist-info/LICENSE
Topsis_Shaurya_101903125-0.0.1.dist-info/METADATA
Topsis_Shaurya_101903125-0.0.1.dist-info/WHEEL
Topsis_Shaurya_101903125-0.0.1.dist-info/entry_points.txt
Topsis_Shaurya_101903125-0.0.1.dist-info/top_level.txt
Topsis_Shaurya_101903125-0.0.1.dist-info/RECORD
